smartini/__init__.py
smartini/args.py
smartini/entities.py
smartini/exceptions_warnings.py
smartini/globals.py
smartini/interface.py
smartini/interface.pyi
smartini/slots.py
smartini/utils.py
smartini/type_converters/__init__.py
smartini/type_converters/converters.py
smartini/type_converters/exceptions.py
smartini/type_converters/type_hints.py
smartini-1.1.3.dist-info/LICENSE
smartini-1.1.3.dist-info/METADATA
smartini-1.1.3.dist-info/WHEEL
smartini-1.1.3.dist-info/top_level.txt
smartini-1.1.3.dist-info/RECORD
